DirNet
