Metadata-Version: 2.1
Name: DirNet
Version: 1.1.1
Summary: Lightweight library for neural network-based directional prediction
Home-page: https://github.com/Foloip
Author: foloip
Author-email: NeuralNetworkTools@gmail.com
License: MIT
Keywords: neural network,direction prediction,ai,machine learning,Perceptron,Backpropagation,relu,sigmoid,loss
Platform: UNKNOWN
License-File: LICENSE
